cpapi/__init__.py
cpapi/api_exceptions.py
cpapi/api_response.py
cpapi/cli.py
cpapi/mgmt_api.py
cpapi/utils.py
cp_mgmt_api_sdk-1.9.0.dist-info/LICENSE
cp_mgmt_api_sdk-1.9.0.dist-info/METADATA
cp_mgmt_api_sdk-1.9.0.dist-info/WHEEL
cp_mgmt_api_sdk-1.9.0.dist-info/top_level.txt
cp_mgmt_api_sdk-1.9.0.dist-info/RECORD
